dungeondice/__init__.py
dungeondice/main.py
dungeondice/discord/__init__.py
dungeondice/discord/templates.py
dungeondice/discord/commandgroups/__init__.py
dungeondice/discord/commandgroups/roll.py
dungeondice/lib/__init__.py
dungeondice/lib/dice.py
dungeondice-1.3.3.dist-info/METADATA
dungeondice-1.3.3.dist-info/WHEEL
dungeondice-1.3.3.dist-info/entry_points.txt
dungeondice-1.3.3.dist-info/licenses/LICENSE
dungeondice-1.3.3.dist-info/RECORD
