Metadata-Version: 2.4
Name: dungeondice
Version: 1.3.3
Summary: Tools to roll some virtual dice
Project-URL: Homepage, https://github.com/jwizzle/dungeondice
Project-URL: Issues, https://github.com/jwizzle/dungeondice/issues
Author-email: jwizzle <info@hossel.net>
License-Expression: GPL-3.0-or-later
License-File: LICENSE
Classifier: Operating System :: OS Independent
Classifier: Programming Language :: Python :: 3
Requires-Python: >=3.8
Requires-Dist: discord-py==2.5.2
Requires-Dist: python-dotenv==1.0.1
